wattpad/__init__.py
wattpad/model_types.py
wattpad/models.py
wattpad/py.typed
wattpad/utils.py
wattpad/wattpad.py
wattpad-1.0.0.dist-info/LICENSE
wattpad-1.0.0.dist-info/METADATA
wattpad-1.0.0.dist-info/WHEEL
wattpad-1.0.0.dist-info/top_level.txt
wattpad-1.0.0.dist-info/RECORD
