Metadata-Version: 2.1
Name: wattpad
Version: 1.0.0
Summary: High-performance Wattpad SDK. Supports Caching and Async. Memory-Efficient.
Home-page: https://github.com/TheOnlyWayUp/Wattpad-Py
Author: TheOnlyWayUp
Author-email: "TheOnlyWayUp" <thedarkdraconian@gmail.com>
Classifier: Operating System :: OS Independent
Classifier: Programming Language :: Python :: 3
Classifier: Programming Language :: Python :: 3 :: Only
Classifier: Programming Language :: Python :: 3.8
Classifier: Programming Language :: Python :: 3.9
Classifier: Programming Language :: Python :: 3.10
Classifier: Programming Language :: Python :: 3.11
Classifier: Programming Language :: Python :: 3.12
Classifier: Programming Language :: Python :: Implementation :: CPython
Classifier: Typing :: Typed
Requires-Python: >=3.8
License-File: LICENSE
Requires-Dist: aiohttp ==3.9.1
Requires-Dist: aiohttp-client-cache ==0.10.0
Requires-Dist: aiosignal ==1.3.1
Requires-Dist: annotated-types ==0.6.0
Requires-Dist: async-timeout ==4.0.3
Requires-Dist: attrs ==23.2.0
Requires-Dist: frozenlist ==1.4.1
Requires-Dist: idna ==3.6
Requires-Dist: itsdangerous ==2.1.2
Requires-Dist: multidict ==6.0.4
Requires-Dist: pydantic ==2.5.3
Requires-Dist: pydantic-core ==2.14.6
Requires-Dist: six ==1.16.0
Requires-Dist: typing-extensions ==4.9.0
Requires-Dist: url-normalize ==1.4.3
Requires-Dist: yarl ==1.9.4
